avanzapy/__init__.py
avanzapy/avanzapy.py
avanzapy/bond.py
avanzapy/certificate.py
avanzapy/constants.py
avanzapy/convertible.py
avanzapy/equitylinkedbond.py
avanzapy/etf.py
avanzapy/fund.py
avanzapy/futureforward.py
avanzapy/historicaldata.py
avanzapy/index.py
avanzapy/instrument.py
avanzapy/instrument_factory.py
avanzapy/option.py
avanzapy/premiumbond.py
avanzapy/stock.py
avanzapy/subscriptionoption.py
avanzapy/warrant.py
avanzapy-0.0.2.dist-info/LICENSE
avanzapy-0.0.2.dist-info/METADATA
avanzapy-0.0.2.dist-info/WHEEL
avanzapy-0.0.2.dist-info/top_level.txt
avanzapy-0.0.2.dist-info/RECORD
