Metadata-Version: 2.1
Name: avanzapy
Version: 0.0.2
Summary: A Python wrapper to interact with Avanza
Home-page: https://github.com/alrevuelta/avanzapy
Author: Alvaro Revuelta
License: UNKNOWN
Keywords: avanza broker trading
Platform: UNKNOWN
Classifier: Development Status :: 3 - Alpha
Classifier: License :: OSI Approved :: MIT License
Classifier: Programming Language :: Python :: 3.6
Requires-Python: >=3.6
Requires-Dist: aiohttp (>=3.6.2)
Requires-Dist: requests (==2.23.0)
Requires-Dist: pandas (==1.0.4)
Requires-Dist: matplotlib (==3.2.1)
